analysistoolbox/__init__.py
analysistoolbox/calculus/FindDerivative.py
analysistoolbox/calculus/FindLimitOfFunction.py
analysistoolbox/calculus/FindMinimumSquareLoss.py
analysistoolbox/calculus/PlotFunction.py
analysistoolbox/calculus/__init__.py
analysistoolbox/data_collection/ExtractTextFromPDF.py
analysistoolbox/data_collection/FetchPDFFromURL.py
analysistoolbox/data_collection/FetchUSShapefile.py
analysistoolbox/data_collection/FetchWebsiteText.py
analysistoolbox/data_collection/GetCompanyFilings.py
analysistoolbox/data_collection/GetGoogleSearchResults.py
analysistoolbox/data_collection/GetZipFile.py
analysistoolbox/data_collection/__init__.py
analysistoolbox/data_processing/AddDateNumberColumns.py
analysistoolbox/data_processing/AddLeadingZeros.py
analysistoolbox/data_processing/AddRowCountColumn.py
analysistoolbox/data_processing/AddTPeriodColumn.py
analysistoolbox/data_processing/AddTukeyOutlierColumn.py
analysistoolbox/data_processing/CleanTextColumns.py
analysistoolbox/data_processing/ConductAnomalyDetection.py
analysistoolbox/data_processing/ConductEntityMatching.py
analysistoolbox/data_processing/ConvertOddsToProbability.py
analysistoolbox/data_processing/CountMissingDataByGroup.py
analysistoolbox/data_processing/CreateBinnedColumn.py
analysistoolbox/data_processing/CreateDataOverview.py
analysistoolbox/data_processing/CreateRandomSampleGroups.py
analysistoolbox/data_processing/CreateRareCategoryColumn.py
analysistoolbox/data_processing/CreateStratifiedRandomSampleGroups.py
analysistoolbox/data_processing/GeocodeUSAddresses.py
analysistoolbox/data_processing/ImputeMissingValuesUsingNearestNeighbors.py
analysistoolbox/data_processing/VerifyGranularity.py
analysistoolbox/data_processing/__init__.py
analysistoolbox/descriptive_analytics/ConductManifoldLearning.py
analysistoolbox/descriptive_analytics/ConductPrincipalComponentAnalysis.py
analysistoolbox/descriptive_analytics/ConductPropensityScoreMatching.py
analysistoolbox-3.9.91.dist-info/LICENSE.md
analysistoolbox-3.9.91.dist-info/METADATA
analysistoolbox-3.9.91.dist-info/WHEEL
analysistoolbox-3.9.91.dist-info/top_level.txt
analysistoolbox-3.9.91.dist-info/RECORD
