Metadata-Version: 2.1
Name: analysistoolbox
Version: 3.9.91
Summary: A collection tools in Python for data collection and processing, statistics, analytics, and intelligence analysis.
Home-page: https://github.com/KyleProtho/AnalysisToolBox/tree/master/analysistoolbox
Author: Kyle Protho
Author-email: kyletprotho@gmail.com
License: MIT
Classifier: Programming Language :: Python :: 3
Classifier: License :: OSI Approved :: MIT License
Classifier: Operating System :: OS Independent
Requires-Python: >=3.9
License-File: LICENSE.md
Provides-Extra: dev
Requires-Dist: pytest >=3.7 ; extra == 'dev'
Requires-Dist: twine >=4.0.2 ; extra == 'dev'
